seoberry/__init__.py
seoberry/cli.py
seoberry/scraper.py
seoberry-1.0.4.dist-info/licenses/LICENSE
seoberry-1.0.4.dist-info/METADATA
seoberry-1.0.4.dist-info/WHEEL
seoberry-1.0.4.dist-info/entry_points.txt
seoberry-1.0.4.dist-info/top_level.txt
seoberry-1.0.4.dist-info/RECORD
