Metadata-Version: 2.4
Name: SEOberry
Version: 1.0.4
Summary: A Python tool to scrape Google rankings of domains for given keywords using Selenium.
Home-page: https://github.com/hamidrezafarzin/SEOberry
Author: Hamidreza Farzin
Author-email: hamidfarzin1382@gmail.com
License: MIT
Project-URL: Source, https://github.com/hamidrezafarzin/SEOberry
Project-URL: Tracker, https://github.com/hamidrezafarzin/SEOberry/issues
Classifier: Intended Audience :: Developers
Classifier: Topic :: Internet :: WWW/HTTP :: Indexing/Search
Classifier: License :: OSI Approved :: MIT License
Classifier: Programming Language :: Python :: 3
Classifier: Programming Language :: Python :: 3.8
Classifier: Programming Language :: Python :: 3.9
Classifier: Programming Language :: Python :: 3.10
Classifier: Programming Language :: Python :: 3.11
Classifier: Operating System :: OS Independent
Requires-Python: >=3.8
License-File: LICENSE
Requires-Dist: selenium>=4.0.0
Requires-Dist: tldextract>=3.0.0
Dynamic: author
Dynamic: author-email
Dynamic: classifier
Dynamic: description
Dynamic: description-content-type
Dynamic: home-page
Dynamic: license
Dynamic: license-file
Dynamic: project-url
Dynamic: requires-dist
Dynamic: requires-python
Dynamic: summary
